json_parser/__init__.py
json_parser/lexer.py
json_parser/parser.py
tests/__init__.py
tests/json_lexer_test.py
tests/json_parser_test.py
json_parser-1.2.0.dist-info/LICENSE
json_parser-1.2.0.dist-info/METADATA
json_parser-1.2.0.dist-info/WHEEL
json_parser-1.2.0.dist-info/top_level.txt
json_parser-1.2.0.dist-info/RECORD
